bomancli/Config.py
bomancli/__init__.py
bomancli/auth.py
bomancli/base_logger.py
bomancli/loc_finder.py
bomancli/main.py
bomancli/utils.py
bomancli/validation.py
boman_cli-0.12.dist-info/METADATA
boman_cli-0.12.dist-info/WHEEL
boman_cli-0.12.dist-info/entry_points.txt
boman_cli-0.12.dist-info/top_level.txt
boman_cli-0.12.dist-info/RECORD
