Metadata-Version: 2.1
Name: boman-cli
Version: 0.12
Summary: python package for boman.ai
Home-page: https://boman.ai
Author: Sumeru Software Solutions Pvt. Ltd.
Author-email: support@boman.ai
License: BSD 2-clause
Platform: UNKNOWN
Classifier: Development Status :: 4 - Beta
Classifier: Intended Audience :: Developers
Classifier: License :: OSI Approved :: BSD License
Classifier: Operating System :: OS Independent
Classifier: Programming Language :: Python :: 3 :: Only
Requires-Dist: coloredlogs
Requires-Dist: docker
Requires-Dist: pyyaml
Requires-Dist: requests
Requires-Dist: xmltodict
